simplelogging/__init__.py
simplelogging-0.12.0.dist-info/AUTHORS.rst
simplelogging-0.12.0.dist-info/LICENSE
simplelogging-0.12.0.dist-info/METADATA
simplelogging-0.12.0.dist-info/WHEEL
simplelogging-0.12.0.dist-info/RECORD
