Metadata-Version: 2.1
Name: simplelogging
Version: 0.12.0
Summary: Logging made simple, no excuse for any debug print call.
Home-page: https://github.com/vpoulailleau/simplelogging
License: BSD-3-Clause
Keywords: logging,simplelogging
Author: Vincent Poulailleau
Author-email: vpoulailleau@gmail.com
Requires-Python: >=3.8,<4.0
Classifier: Development Status :: 4 - Beta
Classifier: Intended Audience :: Developers
Classifier: License :: OSI Approved :: BSD License
Classifier: Natural Language :: English
Classifier: Programming Language :: Python :: 3
Classifier: Programming Language :: Python :: 3.8
Classifier: Programming Language :: Python :: 3.9
Classifier: Programming Language :: Python :: 3.10
Classifier: Programming Language :: Python :: 3.11
Classifier: Programming Language :: Python :: 3.12
Classifier: Topic :: Utilities
Requires-Dist: colorlog (>=4.1.0,<5.0.0)
Project-URL: Documentation, https://simplelogging.readthedocs.io/en/latest/
Project-URL: Repository, https://github.com/vpoulailleau/simplelogging
